LICENSE.txt
README.md
setup.py
src/ThermoBuilPy/__init__.py
src/ThermoBuilPy/component.py
src/ThermoBuilPy/connection.py
src/ThermoBuilPy/storage.py
src/ThermoBuilPy/stratifiedStorage.py
src/ThermoBuilPy/thermalSystem.py
src/ThermoBuilPy.egg-info/PKG-INFO
src/ThermoBuilPy.egg-info/SOURCES.txt
src/ThermoBuilPy.egg-info/dependency_links.txt
src/ThermoBuilPy.egg-info/requires.txt
src/ThermoBuilPy.egg-info/top_level.txt
src/thermobuilpy.egg-info/PKG-INFO
src/thermobuilpy.egg-info/SOURCES.txt
src/thermobuilpy.egg-info/dependency_links.txt
src/thermobuilpy.egg-info/requires.txt
src/thermobuilpy.egg-info/top_level.txt