Metadata-Version: 2.1
Name: thermobuilpy
Version: 0.1.2
Summary: ToDo
Home-page: https://github.com/hanneshanse/MilPython
Author: Hannes Hanse
Author-email: hannes.hanse@tu-clausthal.de
License: MIT
Keywords: milp,time series,optimization,gurobi,gurobipy
Classifier: Programming Language :: Python :: 3
Classifier: License :: OSI Approved :: MIT License
Classifier: Operating System :: OS Independent
License-File: LICENSE.txt
Requires-Dist: numpy
Requires-Dist: matplotlib
